lancelot/__init__.py
lancelot/_lib.cpython-312-darwin.so
lancelot/be2utils/__init__.py
lancelot/be2utils/binexport2_pb2.py
lancelot/be2utils/binexport2_pb2.pyi
python_lancelot-0.9.10.dist-info/METADATA
python_lancelot-0.9.10.dist-info/WHEEL
python_lancelot-0.9.10.dist-info/licenses/LICENSE.txt
python_lancelot-0.9.10.dist-info/RECORD
